setup.py
azrcmd/__init__.py
azrcmd/tests.py
azrcmd.egg-info/PKG-INFO
azrcmd.egg-info/SOURCES.txt
azrcmd.egg-info/dependency_links.txt
azrcmd.egg-info/entry_points.txt
azrcmd.egg-info/not-zip-safe
azrcmd.egg-info/requires.txt
azrcmd.egg-info/top_level.txt