Metadata-Version: 1.0
Name: azrcmd
Version: 0.2.1
Summary: Azure Blob Store command line tool to download and upload files.
Home-page: http://bfaludi.com
Author: Bence Faludi
Author-email: bence@ozmo.hu
License: MIT
Platform: UNKNOWN
